config.py
pqueue.py
dryad_pqueue-0.1.9.dist-info/WHEEL
dryad_pqueue-0.1.9.dist-info/METADATA
dryad_pqueue-0.1.9.dist-info/RECORD
