Metadata-Version: 2.1
Name: dryad-pqueue
Version: 0.1.9
Summary: run models with parameters from a queue and upload to s3 + webhooks
Author: technillogue
Author-email: technillogue@gmail.com
Requires-Python: >=3.9
Classifier: Programming Language :: Python :: 3
Classifier: Programming Language :: Python :: 3.10
Classifier: Programming Language :: Python :: 3.9
Requires-Dist: psycopg[binary,pool] (>=3.0.10,<4.0.0)
Requires-Dist: requests (>=2.28.1,<3.0.0)
